{
  "price_cache": {
    "VWO": {
      "price": 56.8754997253418,
      "timestamp": "2026-02-06T17:53:46.863139"
    },
    "VXUS": {
      "price": 80.56500244140625,
      "timestamp": "2026-02-06T17:53:46.863139"
    },
    "IWM": {
      "price": 261.7699890136719,
      "timestamp": "2026-02-06T17:53:46.863139"
    },
    "SPY": {
      "price": 684.72998046875,
      "timestamp": "2026-02-06T17:53:46.863139"
    },
    "XLV": {
      "price": 156.6300048828125,
      "timestamp": "2026-02-06T17:53:46.863139"
    },
    "VB": {
      "price": 274.4049987792969,
      "timestamp": "2026-02-06T17:53:46.863139"
    },
    "TIP": {
      "price": 110.52999877929688,
      "timestamp": "2026-02-06T17:53:46.863139"
    },
    "XLE": {
      "price": 53.369998931884766,
      "timestamp": "2026-02-06T17:53:46.863139"
    },
    "BND": {
      "price": 74.17350006103516,
      "timestamp": "2026-02-06T17:53:46.863139"
    },
    "AGG": {
      "price": 100.0250015258789,
      "timestamp": "2026-02-06T17:53:46.863139"
    },
    "SCHP": {
      "price": 26.645000457763672,
      "timestamp": "2026-02-06T17:53:46.863139"
    },
    "VHT": {
      "price": 289.2349853515625,
      "timestamp": "2026-02-06T17:53:46.863139"
    },
    "VEA": {
      "price": 66.9749984741211,
      "timestamp": "2026-02-06T17:53:46.863139"
    },
    "VTIP": {
      "price": 49.670101165771484,
      "timestamp": "2026-02-06T17:53:46.863139"
    },
    "VDE": {
      "price": 149.9600067138672,
      "timestamp": "2026-02-06T17:53:46.863139"
    }
  },
  "exchange_rate": {
    "rate": 3.110650062561035,
    "timestamp": "2026-02-06T17:55:10.599931"
  }
}